grymp-0.3.0.dist-info/DESCRIPTION.rst
grymp-0.3.0.dist-info/METADATA
grymp-0.3.0.dist-info/metadata.json
grymp-0.3.0.dist-info/entry_points.txt
grymp-0.3.0.dist-info/top_level.txt
grymp-0.3.0.dist-info/WHEEL
grymp-0.3.0.dist-info/RECORD
grymp/__init__.py
grymp/util.py
grymp/transferer.py
grymp/__main__.py
grymp/tests/test_util.py
grymp/tests/__init__.py
grymp/tests/test_main.py
grymp/tests/processors/test_feature.py
grymp/tests/processors/__init__.py
grymp/tests/processors/test_extras.py
grymp/processors/processor.py
grymp/processors/__init__.py
grymp/processors/feature.py
grymp/processors/extras.py
